Metadata-Version: 2.1
Name: Site-Seo-Scanner
Version: 0.1.0
Summary: The site seo scanner. 
Home-page: https://github.com/onuratakan/Site_Seo_Scanner
Author: Onur Atakan ULUSOY
Author-email: atadogan06@gmail.com
License: MIT
Platform: UNKNOWN
Requires-Python: >=3
